[
  [
    {
      "chapters": 177,
      "countries": 48,
      "city": 174,
      "members": 54631,
      "past_events": 1705,
      "upcoming_events": 83,
      "avgchapter": 3,
      "avgevent": 9,
      "avgmember": 308
    }
  ],
  [
    {
      "latinAm": 38,
      "us_can": 63,
      "eur": 51,
      "afr": 6,
      "asia": 10,
      "aus": 9,
      "latinAm_m": 11009,
      "us_can_m": 18195,
      "eur_m": 17430,
      "afr_m": 1963,
      "asia_m": 2732,
      "aus_m": 3302
    }
  ]
]
