[
  [
    {
      "chapters": 177,
      "countries": 48,
      "city": 174,
      "members": 54424,
      "past_events": 1694,
      "upcoming_events": 82,
      "avgchapter": 3,
      "avgevent": 9,
      "avgmember": 307
    }
  ],
  [
    {
      "latinAm": 38,
      "us_can": 63,
      "eur": 51,
      "afr": 6,
      "asia": 10,
      "aus": 9,
      "latinAm_m": 10971,
      "us_can_m": 18126,
      "eur_m": 17370,
      "afr_m": 1967,
      "asia_m": 2725,
      "aus_m": 3265
    }
  ]
]
