[
  [
    {
      "chapters": 894,
      "countries": 84,
      "city": 407,
      "members": 687913,
      "past_events": 17568,
      "upcoming_events": 370,
      "avgchapter": 10,
      "avgevent": 19,
      "avgmember": 769,
      "last_update": "Sun Nov 24 14:35:29 2019"
    }
  ],
  [
    {
      "latinAm": 94,
      "us_can": 327,
      "eur": 285,
      "afr": 36,
      "asia": 119,
      "aus": 33,
      "latinAm_m": 45564,
      "us_can_m": 302581,
      "eur_m": 200588,
      "afr_m": 17122,
      "asia_m": 96024,
      "aus_m": 26034
    }
  ]
]
