[
  [
    {
      "chapters": 893,
      "countries": 86,
      "city": 409,
      "members": 760812,
      "past_events": 22537,
      "upcoming_events": 339,
      "avgchapter": 10,
      "avgevent": 25,
      "avgmember": 851,
      "last_update": "Thu Dec  3 19:40:21 2020"
    }
  ],
  [
    {
      "latinAm": 106,
      "us_can": 317,
      "eur": 282,
      "afr": 43,
      "asia": 115,
      "aus": 30,
      "latinAm_m": 58951,
      "us_can_m": 329341,
      "eur_m": 220918,
      "afr_m": 22149,
      "asia_m": 102477,
      "aus_m": 26976
    }
  ]
]
