[
  [
    {
      "chapters": 892,
      "countries": 86,
      "city": 414,
      "members": 768035,
      "past_events": 24911,
      "upcoming_events": 527,
      "avgchapter": 10,
      "avgevent": 27,
      "avgmember": 861,
      "last_update": "Mon May 24 19:20:12 2021"
    }
  ],
  [
    {
      "latinAm": 110,
      "us_can": 314,
      "eur": 285,
      "afr": 42,
      "asia": 110,
      "aus": 31,
      "latinAm_m": 61814,
      "us_can_m": 329728,
      "eur_m": 227296,
      "afr_m": 23774,
      "asia_m": 98551,
      "aus_m": 26872
    }
  ]
]
