[
  [
    {
      "chapters": 887,
      "countries": 84,
      "city": 408,
      "members": 757911,
      "past_events": 22797,
      "upcoming_events": 247,
      "avgchapter": 10,
      "avgevent": 25,
      "avgmember": 854,
      "last_update": "Mon Dec 21 18:40:09 2020"
    }
  ],
  [
    {
      "latinAm": 104,
      "us_can": 318,
      "eur": 281,
      "afr": 41,
      "asia": 112,
      "aus": 31,
      "latinAm_m": 59186,
      "us_can_m": 330575,
      "eur_m": 221460,
      "afr_m": 20760,
      "asia_m": 98854,
      "aus_m": 27076
    }
  ]
]
