[
  [
    {
      "chapters": 912,
      "countries": 85,
      "city": 411,
      "members": 732002,
      "past_events": 19632,
      "upcoming_events": 385,
      "avgchapter": 10,
      "avgevent": 21,
      "avgmember": 802,
      "last_update": "Fri Jun 12 16:18:56 2020"
    }
  ],
  [
    {
      "latinAm": 103,
      "us_can": 325,
      "eur": 289,
      "afr": 40,
      "asia": 126,
      "aus": 29,
      "latinAm_m": 52449,
      "us_can_m": 319505,
      "eur_m": 214807,
      "afr_m": 19690,
      "asia_m": 103606,
      "aus_m": 21945
    }
  ]
]
